pytoolboxtwo/__init__.py
pytoolboxtwo/my_module.py
pytoolboxtwo/script.py
pytoolboxtwo-1.0.0.dist-info/METADATA
pytoolboxtwo-1.0.0.dist-info/WHEEL
pytoolboxtwo-1.0.0.dist-info/top_level.txt
pytoolboxtwo-1.0.0.dist-info/RECORD
