Metadata-Version: 2.1
Name: pytoolboxtwo
Version: 1.0.0
Summary: A description of pytoolboxtwo
Home-page: https://github.com/yourusername/pytoolboxtwo
Author: soujanya
Author-email: soujanyaacharya2001@example.com
Requires-Dist: numpy
Requires-Dist: requests
